faramesh/__init__.py
faramesh/canonicalization.py
faramesh/client.py
faramesh/decorators.py
faramesh/gate.py
faramesh/governed_tool.py
faramesh/policy.py
faramesh/policy_helpers.py
faramesh/snapshot.py
faramesh_sdk-0.3.0.dist-info/licenses/LICENSE
tests/test_canonicalization.py
faramesh_sdk-0.3.0.dist-info/METADATA
faramesh_sdk-0.3.0.dist-info/WHEEL
faramesh_sdk-0.3.0.dist-info/top_level.txt
faramesh_sdk-0.3.0.dist-info/RECORD
