Metadata-Version: 2.4
Name: faramesh-sdk
Version: 0.3.0
Summary: Faramesh Python SDK - Production-ready client for the Faramesh Execution Governor API
Author: Faramesh Contributors
License: Elastic License 2.0
Requires-Python: >=3.9
License-File: LICENSE
Requires-Dist: requests>=2.31
Provides-Extra: dev
Requires-Dist: pytest>=7.4; extra == "dev"
Requires-Dist: pytest-asyncio>=0.21; extra == "dev"
Requires-Dist: ruff>=0.3; extra == "dev"
Dynamic: license-file
